calculator/calculator.py
calculator/init.py
tests/init.py
tests/test_calculator.py
calculator_project-0.1.0.dist-info/LICENCE
calculator_project-0.1.0.dist-info/METADATA
calculator_project-0.1.0.dist-info/WHEEL
calculator_project-0.1.0.dist-info/top_level.txt
calculator_project-0.1.0.dist-info/RECORD
