Metadata-Version: 2.1
Name: calculator_project
Version: 0.1.0
Summary: A simple calculator to perform basic arithmetic operations and root calculations.
Home-page: https://github.com/mustafaakgl/Calculator1
Author: Mustafa Akgül
Author-email: Mustafa Akgül <akgul037@gmail.com>
Requires-Python: >=3.6
License-File: LICENCE
